su/logging/__init__.py
su/logging/console.py
su/logging/structured.py
su_logging-1.0.0.dist-info/WHEEL
su_logging-1.0.0.dist-info/METADATA
su_logging-1.0.0.dist-info/RECORD
