Metadata-Version: 2.1
Name: su-logging
Version: 1.0.0
Summary: Logging for Stockholm University
Home-page: https://github.com/stockholmuniversity/su-logging
License: BSD-3-Clause
Author: Simon Lundström
Author-email: simlu+github@su.se
Requires-Python: >=3.5,<4.0
Classifier: License :: OSI Approved :: BSD License
Classifier: Programming Language :: Python :: 3
Classifier: Programming Language :: Python :: 3.5
Classifier: Programming Language :: Python :: 3.6
Classifier: Programming Language :: Python :: 3.7
Classifier: Programming Language :: Python :: 3.8
Classifier: Programming Language :: Python :: 3.9
Provides-Extra: structured
Requires-Dist: logstash_formatter (>=0.5.17,<0.6.0); extra == "structured"
Project-URL: Repository, https://github.com/stockholmuniversity/su-logging
